pie_lock/__init__.py
pie_lock/backends/__init__.py
pie_lock/backends/base_lock.py
pie_lock/backends/distributed_lock/__init__.py
pie_lock/backends/limiter/__init__.py
pie_lock/backends/optimistic_lock/__init__.py
pie_lock/tests/test_distributed_lock.py
pie_lock/tests/test_limiter.py
pie_lock/tests/test_optimistic_lock.py
pie_lock-0.1.7.dist-info/LICENSE
pie_lock-0.1.7.dist-info/WHEEL
pie_lock-0.1.7.dist-info/METADATA
pie_lock-0.1.7.dist-info/RECORD
