Metadata-Version: 2.1
Name: pie-lock
Version: 0.1.7
Summary: A library for python distributed lock, optimistic lock and limiter
Home-page: https://pypi.org/project/pie-lock
Keywords: distributed lock,lock,redis lock,limiter
Author: TuanDC
Author-email: tuandao864@gmail.com
Maintainer: TuanDC
Maintainer-email: tuandao864@gmail.com
Requires-Python: >=3.6.2,<4.0.0
Classifier: Programming Language :: Python :: 3
Classifier: Programming Language :: Python :: 3.7
Classifier: Programming Language :: Python :: 3.8
Classifier: Programming Language :: Python :: 3.9
Classifier: Programming Language :: Python :: 3.10
Classifier: Programming Language :: Python :: 3.11
Requires-Dist: arrow (>=1.2.2,<2.0.0)
Requires-Dist: async-timeout (>=4.0.2,<5.0.0)
Requires-Dist: inflection (>=0.5.1,<0.6.0)
Requires-Dist: redis (>=4.4.0,<5.0.0)
Project-URL: Repository, https://github.com/HKer-MuCoi/pielock
